{
  "indexes": [
    {
      "collectionGroup": "faxSchedules",
      "queryScope": "COLLECTION",
      "fields": [
        {
          "fieldPath": "status",
          "order": "ASCENDING"
        },
        {
          "fieldPath": "createdDatetime",
          "order": "ASCENDING"
        }
      ]
    },
    {
      "collectionGroup": "faxSchedules",
      "queryScope": "COLLECTION",
      "fields": [
        {
          "fieldPath": "status",
          "order": "ASCENDING"
        },
        {
          "fieldPath": "scheduledDatetime",
          "order": "ASCENDING"
        }
      ]
    },
    {
      "collectionGroup": "faxSchedules",
      "queryScope": "COLLECTION",
      "fields": [
        {
          "fieldPath": "status",
          "order": "ASCENDING"
        },
        {
          "fieldPath": "scheduledDatetime",
          "order": "ASCENDING"
        },
        {
          "fieldPath": "createdDatetime",
          "order": "ASCENDING"
        }
      ]
    }
  ],
  "fieldOverrides": []
}
